trivialpy/__init__.py
trivialpy/main.py
trivialpy/preguntas.py
trivialpy-0.0.8.dist-info/licenses/LICENSE
trivialpy-0.0.8.dist-info/METADATA
trivialpy-0.0.8.dist-info/WHEEL
trivialpy-0.0.8.dist-info/top_level.txt
trivialpy-0.0.8.dist-info/RECORD
