Metadata-Version: 2.4
Name: TrivialPy
Version: 0.0.8
Summary: Pequeño juego de preguntas de cultura general realizado en Python
Author: Inés Martínez (cvcvrril) 𓁹‿𓁹
Requires-Python: >=3.10
License-File: LICENSE
Dynamic: license-file
